odoo/addons/so_sequence_confirmed_order_base/README.rst
odoo/addons/so_sequence_confirmed_order_base/__init__.py
odoo/addons/so_sequence_confirmed_order_base/__manifest__.py
odoo/addons/so_sequence_confirmed_order_base/i18n/es.po
odoo/addons/so_sequence_confirmed_order_base/models/__init__.py
odoo/addons/so_sequence_confirmed_order_base/models/res_company.py
odoo/addons/so_sequence_confirmed_order_base/models/res_config_settings.py
odoo/addons/so_sequence_confirmed_order_base/models/sale_order.py
odoo/addons/so_sequence_confirmed_order_base/static/description/icon.png
odoo/addons/so_sequence_confirmed_order_base/views/res_config_settings_view.xml
odoo_addon_so_sequence_confirmed_order_base-15.0.1.0.0.2.dist-info/METADATA
odoo_addon_so_sequence_confirmed_order_base-15.0.1.0.0.2.dist-info/WHEEL
odoo_addon_so_sequence_confirmed_order_base-15.0.1.0.0.2.dist-info/top_level.txt
odoo_addon_so_sequence_confirmed_order_base-15.0.1.0.0.2.dist-info/RECORD
